ppdm/__init__.py
ppdm/rjcli.py
rjcli-1.0.5.dist-info/LICENSE
rjcli-1.0.5.dist-info/METADATA
rjcli-1.0.5.dist-info/WHEEL
rjcli-1.0.5.dist-info/entry_points.txt
rjcli-1.0.5.dist-info/top_level.txt
rjcli-1.0.5.dist-info/RECORD
