Metadata-Version: 2.1
Name: rjcli
Version: 1.0.5
Summary: CLI Interface for PPDM
Home-page: https://github.com/rjainoje/rjcli
Author: Raghava Jainoje
Author-email: 
License: MIT
Platform: UNKNOWN
Classifier: Programming Language :: Python :: 3.8
Classifier: License :: OSI Approved :: MIT License
Classifier: Operating System :: OS Independent
License-File: LICENSE
Requires-Dist: click (>=7.1.2)
Requires-Dist: click-shell (>=2.0)
Requires-Dist: DateTime (>=4.3)
Requires-Dist: pyfiglet (>=0.8.post1)
Requires-Dist: requests (>=2.23.0)
Requires-Dist: tabulate (>=0.8.7)
Requires-Dist: urllib3 (>=1.25.9)
